openfermionpsi4/__init__.py
openfermionpsi4/_psi4_conversion_functions.py
openfermionpsi4/_psi4_template
openfermionpsi4/_run_psi4.py
openfermionpsi4/_version.py
openfermionpsi4-0.5.dist-info/LICENSE
openfermionpsi4-0.5.dist-info/METADATA
openfermionpsi4-0.5.dist-info/NOTICE
openfermionpsi4-0.5.dist-info/WHEEL
openfermionpsi4-0.5.dist-info/top_level.txt
openfermionpsi4-0.5.dist-info/RECORD
