Metadata-Version: 1.0
Name: openfermionpsi4
Version: 0.5
Summary: A plugin allowing OpenFermion to interface with Psi4.
Home-page: https://www.openfermion.org/
Author: The OpenFermion Developers
Author-email: help@openfermiong.org
License: GNU Lesser General Public License (LGPL), Version 3 or any later version
Platform: UNKNOWN
